ChangeLog
LICENSE.txt
README.md
pyproject.toml
ecscmdb/__init__.py
ecscmdb/api.py
ecscmdb/cmdb.py
ecscmdb/cmdbdiff.py
ecscmdb/finddifferences.py
ecscmdb/format.py
ecscmdb/parseargsCMDB.py
ecscmdb/parseargsCMDBDIFF.py
ecscmdb/summary.py
ecscmdb/updatecells.py
ecscmdb-2.0.5.dist-info/LICENSE.txt
ecscmdb-2.0.5.dist-info/METADATA
ecscmdb-2.0.5.dist-info/WHEEL
ecscmdb-2.0.5.dist-info/entry_points.txt
ecscmdb-2.0.5.dist-info/RECORD
