Metadata-Version: 2.1
Name: ecscmdb
Version: 2.0.5
Summary: Dump the OpenManage database.
License: GPL-3.0-or-later
Keywords: cmdb,cmdbdiff
Author: Thomas R. Stevenson
Author-email: aa0026@wayne.edu
Maintainer: Thomas R. Stevenson
Maintainer-email: aa0026@wayne.edu
Requires-Python: >=3.11,<4.0
Classifier: Development Status :: 3 - Alpha
Classifier: Environment :: Console
Classifier: License :: OSI Approved :: GNU General Public License v3 or later (GPLv3+)
Classifier: License :: OSI Approved :: Python Software Foundation License
Classifier: Operating System :: OS Independent
Classifier: Programming Language :: Python :: 3
Classifier: Programming Language :: Python :: 3.11
Classifier: Programming Language :: Python :: 3.12
Classifier: Topic :: Software Development :: User Interfaces
Requires-Dist: ECSpylibs (>=2.0.2,<3.0.0)
Requires-Dist: autologging (>=1.3.2,<2.0.0)
Requires-Dist: certifi (>=2023.11.17,<2024.0.0)
Requires-Dist: charset-normalizer (>=3.3.2,<4.0.0)
Requires-Dist: docopt (>=0.6.2,<0.7.0)
Requires-Dist: et-xmlfile (>=1.1.0,<2.0.0)
Requires-Dist: idna (>=3.6,<4.0)
Requires-Dist: jinja2 (>=3.1.2,<4.0.0)
Requires-Dist: lxml (>=4.9.4,<5.0.0)
Requires-Dist: markupsafe (>=2.1.3,<3.0.0)
Requires-Dist: numpy (>=1.26.2,<2.0.0)
Requires-Dist: openpyxl (>=3.1.2,<4.0.0)
Requires-Dist: pandas (>=2.1.4,<3.0.0)
Requires-Dist: pycryptodome (>=3.19.0,<4.0.0)
Requires-Dist: python-dateutil (>=2.8.2,<3.0.0)
Requires-Dist: pytz (>=2023.3.post1,<2024.0)
Requires-Dist: pyyaml (>=6.0.1,<7.0.0)
Requires-Dist: requests (>=2.31.0,<3.0.0)
Requires-Dist: six (>=1.16.0,<2.0.0)
Requires-Dist: toml (>=0.10.2,<0.11.0)
Requires-Dist: tzdata (>=2023.3,<2024.0)
Requires-Dist: urllib3 (>=2.1.0,<3.0.0)
Requires-Dist: xlrd (>=2.0.1,<3.0.0)
Requires-Dist: xlsxwriter (>=3.1.9,<4.0.0)
Requires-Dist: xmltodict (>=0.13.0,<0.14.0)
Project-URL: About Me, https://About.Me/Thomas.R.Stevenson
Project-URL: License, https://git.wayne.edu/ECS_Projects/ECScmdb/-/blob/master/LICENSE.txt
